terrajinja/sbp/vcd/__init__.py
terrajinja/sbp/vcd/data_vcd_catalog_vapp_template.py
terrajinja/sbp/vcd/data_vcd_nsxt_alb_edgegateway_service_engine_group.py
terrajinja/sbp/vcd/data_vcd_vm_placement_policy.py
terrajinja/sbp/vcd/decorators.py
terrajinja/sbp/vcd/network_isolated_v2.py
terrajinja/sbp/vcd/network_routed_v2.py
terrajinja/sbp/vcd/nsxt_alb_pool.py
terrajinja/sbp/vcd/nsxt_alb_virtual_service.py
terrajinja/sbp/vcd/nsxt_app_port_profile.py
terrajinja/sbp/vcd/nsxt_distributed_firewall.py
terrajinja/sbp/vcd/nsxt_edge_firewall.py
terrajinja/sbp/vcd/nsxt_edge_loadbalancer.py
terrajinja/sbp/vcd/nsxt_firewall_rule_parser.py
terrajinja/sbp/vcd/nsxt_ip_set.py
terrajinja/sbp/vcd/nsxt_nat_rule.py
terrajinja/sbp/vcd/palo_alto.py
terrajinja/sbp/vcd/palo_alto_iso_builder.py
terrajinja/sbp/vcd/rde.py
terrajinja/sbp/vcd/vm.py
terrajinja/sbp/vcd/vm_internal_disk.py
terrajinja_sbp_vcd-0.10.0.dist-info/LICENSE
terrajinja_sbp_vcd-0.10.0.dist-info/METADATA
terrajinja_sbp_vcd-0.10.0.dist-info/WHEEL
terrajinja_sbp_vcd-0.10.0.dist-info/top_level.txt
terrajinja_sbp_vcd-0.10.0.dist-info/RECORD
