Metadata-Version: 2.1
Name: terrajinja-sbp-vcd
Version: 0.10.0
Summary: Terrajinja extension for automation using cdktf
Home-page: https://gitlab/terrajinja
Author: Terrajinja Team
Author-email: int-terrajinja@schubergphilis.com
License: MIT
Classifier: Development Status :: 4 - Beta
Classifier: Intended Audience :: Developers
Classifier: License :: OSI Approved :: MIT License
Classifier: Natural Language :: English
Classifier: Programming Language :: Python :: 3.11
License-File: LICENSE
Requires-Dist: terrajinja-imports-vcd >=3.11.0
Requires-Dist: terrajinja-sbp-generic >=0.0.1
Requires-Dist: cdktf-cdktf-provider-time >=10.0.0
Requires-Dist: cdktf-cdktf-provider-vault >=12.1.0
Requires-Dist: pycdlib >=1.14.0
